odoo/addons/purchase_cancel_remaining_delivery/README.rst
odoo/addons/purchase_cancel_remaining_delivery/__init__.py
odoo/addons/purchase_cancel_remaining_delivery/__manifest__.py
odoo/addons/purchase_cancel_remaining_delivery/i18n/it.po
odoo/addons/purchase_cancel_remaining_delivery/i18n/purchase_cancel_remaining_delivery.pot
odoo/addons/purchase_cancel_remaining_delivery/models/__init__.py
odoo/addons/purchase_cancel_remaining_delivery/models/purchase_order.py
odoo/addons/purchase_cancel_remaining_delivery/readme/CONTRIBUTORS.rst
odoo/addons/purchase_cancel_remaining_delivery/readme/DESCRIPTION.rst
odoo/addons/purchase_cancel_remaining_delivery/static/description/icon.png
odoo/addons/purchase_cancel_remaining_delivery/static/description/index.html
odoo/addons/purchase_cancel_remaining_delivery/tests/__init__.py
odoo/addons/purchase_cancel_remaining_delivery/tests/test_purchase_cancel_remaining_delivery.py
odoo/addons/purchase_cancel_remaining_delivery/views/purchase_order.xml
odoo14_addon_purchase_cancel_remaining_delivery-14.0.1.0.1.dev4.dist-info/METADATA
odoo14_addon_purchase_cancel_remaining_delivery-14.0.1.0.1.dev4.dist-info/WHEEL
odoo14_addon_purchase_cancel_remaining_delivery-14.0.1.0.1.dev4.dist-info/top_level.txt
odoo14_addon_purchase_cancel_remaining_delivery-14.0.1.0.1.dev4.dist-info/RECORD
